structy.py
structy-2021.3.3.dist-info/WHEEL
structy-2021.3.3.dist-info/METADATA
structy-2021.3.3.dist-info/RECORD
