Metadata-Version: 2.1
Name: structy
Version: 2021.3.3
Summary: Structy runtime components for Python
Home-page: https://github.com/theacodes/structy
License: UNKNOWN
Author: Alethea Katherine Flowers
Author-email: thea@winterbloom.com
Classifier: License :: OSI Approved :: MIT License
